nestedmodels/__init__.py
nestedmodels/encoder.py
nestedmodels/models.py
nested_models-0.1.1.dist-info/LICENSE
nested_models-0.1.1.dist-info/METADATA
nested_models-0.1.1.dist-info/WHEEL
nested_models-0.1.1.dist-info/top_level.txt
nested_models-0.1.1.dist-info/RECORD
