Metadata-Version: 2.1
Name: nested-models
Version: 0.1.1
Summary: Simple Model objects that can be validated and serialized/deserialized into various formats.
Home-page: https://github.com/renderbox/django-permafrost/
Author: Grant Viklund
Author-email: renderbox@gmail.com
License: MIT license
Keywords: serialization,json,yaml
Platform: UNKNOWN
Classifier: Development Status :: 2 - Pre-Alpha
Classifier: Intended Audience :: Developers
Classifier: Programming Language :: Python :: 3 :: Only
Classifier: Programming Language :: Python :: 3.6
Classifier: Programming Language :: Python :: 3.7
Requires-Python: >=3.6
Provides-Extra: build
Requires-Dist: setuptools ; extra == 'build'
Requires-Dist: wheel ; extra == 'build'
Requires-Dist: twine ; extra == 'build'
Provides-Extra: docs
Requires-Dist: coverage ; extra == 'docs'
Requires-Dist: Sphinx ; extra == 'docs'
